scatrex/__init__.py
scatrex/callbacks.py
scatrex/models/__init__.py
scatrex/models/cna/__init__.py
scatrex/models/cna/node.py
scatrex/models/cna/tree.py
scatrex/ntssb/__init__.py
scatrex/ntssb/node.py
scatrex/ntssb/ntssb.py
scatrex/ntssb/search.py
scatrex/ntssb/tree.py
scatrex/ntssb/tssb.py
scatrex/plotting/__init__.py
scatrex/plotting/constants.py
scatrex/plotting/scatterplot.py
scatrex/scatrex.py
scatrex/util.py
scatrex-0.2.0.dist-info/LICENSE
scatrex-0.2.0.dist-info/WHEEL
scatrex-0.2.0.dist-info/METADATA
scatrex-0.2.0.dist-info/RECORD
